{
    "sarah-kahn-hair": "sarah@sarahkahnhair.com",
    "pearl-bar-and-dining": "bradley@pearlbellevue.com",
    "po-dog": "info@podogs.com",
    "ride-the-ducks-of-seattle": "trisha@ridetheducksseattle.com",
    "auto-battery": "hr@podogs.com",
    "bremerton-bar-and-grill": "bremerton@neighborhoodgrills.com",
    "rock-salt-steak-and-seafood": "rocksaltfb@gmail.com",
    "mcmenamins-six-arms": "reneer@hq.mcmenamin.com",
    "perqulator": "seanwthomas@perqulator.com",
    "american-cutting-co.": "steve@americancuttingco.com",
    "the-original-childrens-shop": "theoriginalchildrensshop@gmail.com",
    "jackstraw": "paola@jstraw.com",
    "dish-it-up": "cook@dish-it-up.com",
    "museum-of-flight": "thuetter@museumofflight.org",
    "grand-hyatt-seattle": "lorraine.chan@hyatt.com",
    "tours-northwest-/-seattle-tours": "info@toursnorthwest.com",
    "the-westin-seattle": "irene.lin@westin.com",
    "vintage-park": "anthony.baliola@vintagepark.com",
    "urban-kitchen-company": "info@urbankitchencompany.com",
    "crossroads-bar-and-grill": "crossroads@neighborhoodgrills.com",
    "ian": "cerise@ianshop.com",
    "eastlake-bar-and-grill": "eastlake@neighborhoodgrills.com",
    "wild-ginger-at-the-bravern": "wgsocialmedia@wildginger.net",
    "alexis-hotel": "lyndsay.liberty@alexishotel.com",
    "grims": "grimseattle@gmail.com",
    "the-triple-door": "3dsocialmedia@thetripledoor.net",
    "lecosho": "jill@lecosho.com",
    "pirkko": "info@pirkko.com",
    "matador": "christie@matadorrestaurants.com",
    "spaahh": "vivian.weber@hotel1000seattle.com",
    "oxbox-gym": "info@oxboxgym.com",
    "greenlake-bar-and-grill": "greenlake@neighborhoodgrills.com",
    "caffe-vita-fremont": "lucia@caffevita.com",
    "seattle-art-museum": "carlosg@seattleartmuseum.org"
}